webhook_gateway/__init__.py
webhook_gateway/api.py
webhook_gateway/configuration.py
webhook_gateway/exceptions.py
webhook_gateway/main.py
webhook_gateway/request.py
webhook_gateway/router.py
webhook_gateway/routes/__init__.py
webhook_gateway/routes/exceptions.py
webhook_gateway/routes/route.py
webhook_gateway/routes/rules/__init__.py
webhook_gateway/routes/rules/input.py
webhook_gateway/routes/rules/output.py
webhook_gateway/routes/service.py
webhook_gateway-0.1.0.dist-info/LICENSE
webhook_gateway-0.1.0.dist-info/WHEEL
webhook_gateway-0.1.0.dist-info/METADATA
webhook_gateway-0.1.0.dist-info/RECORD
